MANIFEST.in
README.rst
setup.py
floodberry.poly1305_donna/README.md
floodberry.poly1305_donna/example-poly1305.c
floodberry.poly1305_donna/poly1305-donna-16.h
floodberry.poly1305_donna/poly1305-donna-32.h
floodberry.poly1305_donna/poly1305-donna-64.h
floodberry.poly1305_donna/poly1305-donna-8.h
floodberry.poly1305_donna/poly1305-donna.c
floodberry.poly1305_donna/poly1305-donna.h
poly1305_donna/__init__.py
poly1305_donna/benchmark.py
poly1305_donna/test.py
poly1305_donna.egg-info/PKG-INFO
poly1305_donna.egg-info/SOURCES.txt
poly1305_donna.egg-info/dependency_links.txt
poly1305_donna.egg-info/requires.txt
poly1305_donna.egg-info/top_level.txt
poly1305_donna.egg-info/zip-safe
poly1305_donna/doc/LICENSE-MIT.txt
poly1305_donna/doc/README.md
poly1305_donna/doc/README.rst