Metadata-Version: 1.1
Name: poly1305-donna
Version: 0.11.15
Summary: Python wrapper around poly1305_donna by floodberry
Home-page: https://github.com/sundarnagarajan/py_poly1305-donna
Author: Sundar Nagarajan
Author-email: UNKNOWN
License: License :: OSI Approved :: MIT License
Download-URL: https://github.com/sundarnagarajan/py_poly1305-donna/tree/0.11.15
Platform: UNKNOWN
Classifier: Development Status :: 4 - Beta
Classifier: Programming Language :: Python :: 2
Classifier: Programming Language :: Python :: 3
Classifier: Programming Language :: Python :: Implementation :: PyPy
Classifier: License :: OSI Approved :: MIT License
